LaplaceDiff/LaplaceDiff.py
LaplaceDiff/__init__.py
LaplaceDiff/elemental.py
LaplaceDiff/UnitTests/__init__.py
LaplaceDiff/UnitTests/test_LaplaceDiff.py
LaplaceDiff/UnitTests/test_elemental.py
LaplaceDiff-0.1.0.dist-info/METADATA
LaplaceDiff-0.1.0.dist-info/WHEEL
LaplaceDiff-0.1.0.dist-info/top_level.txt
LaplaceDiff-0.1.0.dist-info/RECORD
